macro_check/__init__.py
macro_check/checker.py
macro_check-0.1.0.dist-info/METADATA
macro_check-0.1.0.dist-info/WHEEL
macro_check-0.1.0.dist-info/top_level.txt
macro_check-0.1.0.dist-info/RECORD
