Metadata-Version: 2.1
Name: macro-check
Version: 0.1.0
Summary: Macro detection for documents
Home-page: UNKNOWN
Author: Your Name
Author-email: you@example.com
License: UNKNOWN
Platform: UNKNOWN
Classifier: Programming Language :: Python :: 3
Classifier: Operating System :: OS Independent
Requires-Dist: oletools
Requires-Dist: PyMuPDF
